kittychat/__init__.py
kittychat/errors.py
kittychat/msg_dropping/__init__.py
kittychat/msg_dropping/msg_dropper.py
kittychat-0.1.4.dist-info/METADATA
kittychat-0.1.4.dist-info/WHEEL
kittychat-0.1.4.dist-info/top_level.txt
kittychat-0.1.4.dist-info/RECORD
