Metadata-Version: 2.1
Name: kittychat
Version: 0.1.4
Summary: The cat's meow in AI conversation management.
Home-page: https://github.com/TeiaLabs/kittychat
Author: TeiaLabs
Author-email: contato@teialabs.com
Requires-Python: >=3.11
Requires-Dist: totokenizers >=1.0.2
